crczp/aws_driver/__init__.py
crczp/aws_driver/aws_client.py
crczp/aws_driver/exceptions.py
crczp/aws_driver/templates/security-groups-template.j2
crczp/aws_driver/templates/terraform-deploy-template.j2
crczp/aws_driver/templates/terraform-provider-template.j2
crczp_aws_lib-1.0.2.dist-info/METADATA
crczp_aws_lib-1.0.2.dist-info/WHEEL
crczp_aws_lib-1.0.2.dist-info/licenses/LICENSE
crczp_aws_lib-1.0.2.dist-info/RECORD
