Metadata-Version: 2.4
Name: crczp-aws-lib
Version: 1.0.2
Summary: Cyberrangecz platform AWS Driver Python lib
Project-URL: GitHub, https://github.com/cyberrangecz/backend-aws-lib
Author-email: Juraj Paluba <4492988@mail.muni.cz>
License-Expression: MIT
License-File: LICENSE
Requires-Python: >=3.9
Requires-Dist: boto3>=1.38.40
Requires-Dist: crczp-python-commons~=1.0.1
Requires-Dist: jinja2>=3.1.3
Requires-Dist: pyyaml>=6.0.2
